artd/__init__.py
artd/asgi.py
artd/settings.py
artd/urls.py
artd/wsgi.py
artd_nequi/__init__.py
artd_nequi/admin.py
artd_nequi/apps.py
artd_nequi/models.py
artd_nequi/tests.py
artd_nequi/views.py
artd_nequi/__pycache__/__init__.cpython-310.pyc
artd_nequi/__pycache__/admin.cpython-310.pyc
artd_nequi/__pycache__/apps.cpython-310.pyc
artd_nequi/__pycache__/models.cpython-310.pyc
artd_nequi/migrations/0001_initial.py
artd_nequi/migrations/0002_alter_nequicredential_partner.py
artd_nequi/migrations/0003_nequicredential_test_cellphone_and_more.py
artd_nequi/migrations/0004_remove_nequitransaction_transaction_id_and_more.py
artd_nequi/migrations/0005_alter_nequitransaction_other_data.py
artd_nequi/migrations/0006_nequitransaction_transaction_id.py
artd_nequi/migrations/0007_nequitransaction_value_nequitransactionhisory.py
artd_nequi/migrations/0008_alter_nequitransactionhisory_name_and_more.py
artd_nequi/migrations/__init__.py
artd_nequi/migrations/__pycache__/0001_initial.cpython-310.pyc
artd_nequi/migrations/__pycache__/0002_alter_nequicredential_partner.cpython-310.pyc
artd_nequi/migrations/__pycache__/0003_nequicredential_test_cellphone_and_more.cpython-310.pyc
artd_nequi/migrations/__pycache__/0004_remove_nequitransaction_transaction_id_and_more.cpython-310.pyc
artd_nequi/migrations/__pycache__/0005_alter_nequitransaction_other_data.cpython-310.pyc
artd_nequi/migrations/__pycache__/0006_nequitransaction_transaction_id.cpython-310.pyc
artd_nequi/migrations/__pycache__/0007_nequitransaction_value_nequitransactionhisory.cpython-310.pyc
artd_nequi/migrations/__pycache__/0008_alter_nequitransactionhisory_name_and_more.cpython-310.pyc
artd_nequi/migrations/__pycache__/__init__.cpython-310.pyc
artd_nequi/utils/__init__.py
artd_nequi/utils/nequi_util.py
artd_nequi/utils/__pycache__/__init__.cpython-310.pyc
artd_nequi/utils/__pycache__/nequi_util.cpython-310.pyc
artd_nequi-0.0.1.dist-info/LICENSE
artd_nequi-0.0.1.dist-info/METADATA
artd_nequi-0.0.1.dist-info/WHEEL
artd_nequi-0.0.1.dist-info/top_level.txt
artd_nequi-0.0.1.dist-info/RECORD
