Metadata-Version: 2.1
Name: artd-nequi
Version: 0.0.1
Summary: A Django app to integrato with Nequi payment gateway
Home-page: https://www.artd.com.co/
Author: Jonathan Urzola Maladonado
Author-email: jonathan@artd.com.co
Keywords: pypi,cicd,python
Classifier: Environment :: Web Environment
Classifier: Framework :: Django
Classifier: Framework :: Django :: 4.2
Classifier: Intended Audience :: Developers
Classifier: License :: OSI Approved :: BSD License
Classifier: Operating System :: OS Independent
Classifier: Programming Language :: Python
Classifier: Programming Language :: Python :: 3
Classifier: Programming Language :: Python :: 3 :: Only
Classifier: Programming Language :: Python :: 3.8
Classifier: Programming Language :: Python :: 3.9
Classifier: Topic :: Internet :: WWW/HTTP
Classifier: Topic :: Internet :: WWW/HTTP :: Dynamic Content
License-File: LICENSE
